glassdome_waypoint_sdk/__init__.py
glassdome_waypoint_sdk/registry.py
glassdome_waypoint_sdk/_internal/__init__.py
glassdome_waypoint_sdk/_internal/auth.py
glassdome_waypoint_sdk/_internal/client.py
glassdome_waypoint_sdk/_internal/config.py
glassdome_waypoint_sdk/_internal/error.py
glassdome_waypoint_sdk/_internal/retry.py
glassdome_waypoint_sdk/api/__init__.py
glassdome_waypoint_sdk/api/buf/__init__.py
glassdome_waypoint_sdk/api/buf/validate/__init__.py
glassdome_waypoint_sdk/api/buf/validate/validate_pb2.py
glassdome_waypoint_sdk/api/buf/validate/validate_pb2.pyi
glassdome_waypoint_sdk/api/errdetails/__init__.py
glassdome_waypoint_sdk/api/errdetails/error_details_pb2.py
glassdome_waypoint_sdk/api/errdetails/error_details_pb2.pyi
glassdome_waypoint_sdk/api/external/__init__.py
glassdome_waypoint_sdk/api/external/waypoint/__init__.py
glassdome_waypoint_sdk/api/external/waypoint/v1beta1/__init__.py
glassdome_waypoint_sdk/api/external/waypoint/v1beta1/operation_pb2.py
glassdome_waypoint_sdk/api/external/waypoint/v1beta1/operation_pb2.pyi
glassdome_waypoint_sdk/api/external/waypoint/v1beta1/pcf_pb2.py
glassdome_waypoint_sdk/api/external/waypoint/v1beta1/pcf_pb2.pyi
glassdome_waypoint_sdk/api/external/waypoint/v1beta1/product_pb2.py
glassdome_waypoint_sdk/api/external/waypoint/v1beta1/product_pb2.pyi
glassdome_waypoint_sdk/api/external/waypoint/v1beta1/site_pb2.py
glassdome_waypoint_sdk/api/external/waypoint/v1beta1/site_pb2.pyi
glassdome_waypoint_sdk/api/external/waypoint/v1beta1/waypoint_pb2.py
glassdome_waypoint_sdk/api/external/waypoint/v1beta1/waypoint_pb2.pyi
glassdome_waypoint_sdk/api/google/api/annotations_pb2.py
glassdome_waypoint_sdk/api/google/api/annotations_pb2.pyi
glassdome_waypoint_sdk/api/google/api/http_pb2.py
glassdome_waypoint_sdk/api/google/api/http_pb2.pyi
glassdome_waypoint_sdk/api/google/rpc/status_pb2.py
glassdome_waypoint_sdk/api/google/rpc/status_pb2.pyi
glassdome_waypoint_sdk/api/protoc_gen_openapiv2/__init__.py
glassdome_waypoint_sdk-0.1.1.dist-info/METADATA
glassdome_waypoint_sdk-0.1.1.dist-info/WHEEL
glassdome_waypoint_sdk-0.1.1.dist-info/top_level.txt
glassdome_waypoint_sdk-0.1.1.dist-info/RECORD
