Metadata-Version: 2.4
Name: glassdome-waypoint-sdk
Version: 0.1.1
Summary: Python SDK for Glassdome Waypoint API.
Author-email: Glassdome <developer@glassdomeinc.com>
License: Proprietary
Requires-Python: >=3.9
Requires-Dist: requests>=2.28.0
Requires-Dist: protobuf>=6.33.0
Requires-Dist: googleapis-common-protos>=1.60.0
